__init__.py
exceptions.py
git_utils.py
mcp_server.py
ai/client.py
ai/prompts.py
cli/main.py
cli/ui.py
config/__init__.py
config/settings.py
tama_cli-0.1.1.dist-info/licenses/LICENSE
task_manager/__init__.py
task_manager/complexity.py
task_manager/core.py
task_manager/data_models.py
task_manager/dependencies.py
task_manager/expansion.py
task_manager/file_generator.py
task_manager/parsing.py
task_manager/storage.py
task_manager/storage_sqlite.py
tama_cli-0.1.1.dist-info/METADATA
tama_cli-0.1.1.dist-info/WHEEL
tama_cli-0.1.1.dist-info/entry_points.txt
tama_cli-0.1.1.dist-info/top_level.txt
tama_cli-0.1.1.dist-info/RECORD
