Metadata-Version: 2.4
Name: tama-cli
Version: 0.1.1
Summary: 一个由 AI 驱动的任务管理命令行工具
Author-email: Your Name <youremail@example.com>
Classifier: Programming Language :: Python :: 3
Classifier: License :: OSI Approved :: MIT License
Classifier: Operating System :: OS Independent
Requires-Python: >=3.10
License-File: LICENSE
Requires-Dist: mcp[cli]>=1.6.0
Requires-Dist: openai>=1.10.0
Requires-Dist: pytest>=7.4.0
Requires-Dist: pytest-mock>=3.10.0
Requires-Dist: python-dotenv>=1.0.0
Requires-Dist: rich>=13.0.0
Requires-Dist: typer>=0.9.0
Requires-Dist: pydantic
Dynamic: license-file
